pyrollup/__init__.py
pyrollup-0.1.0.dist-info/LICENSE
pyrollup-0.1.0.dist-info/METADATA
pyrollup-0.1.0.dist-info/WHEEL
pyrollup-0.1.0.dist-info/RECORD
