Metadata-Version: 2.1
Name: pyrollup
Version: 0.1.0
Summary: Simple mechanism to rollup API symbols to a Python module from its submodules
Home-page: https://github.com/mm21/pyrollup
Author: mm21
Author-email: mm21.apps@gmail.com
Requires-Python: >=3.10,<4.0
Classifier: Development Status :: 3 - Alpha
Classifier: License :: OSI Approved :: MIT License
Classifier: Natural Language :: English
Classifier: Operating System :: OS Independent
Classifier: Programming Language :: Python :: 3
Classifier: Programming Language :: Python :: 3.10
Classifier: Programming Language :: Python :: 3.11
Classifier: Programming Language :: Python :: Implementation :: CPython
Classifier: Topic :: Software Development :: Libraries :: Python Modules
Classifier: Typing :: Typed
